{
  "title": "POSLEDNÉ ZÁTIŠIE",
  "author": "SCHUBERT, JÚLIUS",
  "year": "1947",
  "id": "SNG-0001009770",
  "width": 1600,
  "height": 2048,
  "file": "GNZ--M_610--1_1--2015_01_09--L2_WEB_11412.webp",
  "tiles_x": 3,
  "tiles_y": 3,
  "offset_x": 0.0,
  "offset_y": 0.109375,
  "tiles": [
    {
      "margin": false,
      "index": 6,
      "file": null,
      "u": 0.0,
      "v": 0.109375,
      "uw": 0.3333333,
      "vh": 0.260416657,
      "width": 533,
      "height": 533,
      "descriptor": [
        77,
        82,
        83,
        69,
        69,
        67,
        62,
        65,
        67,
        62,
        69,
        67,
        63,
        80,
        83,
        53,
        57,
        58,
        112,
        123,
        107,
        127,
        102,
        98,
        67,
        93,
        96,
        110,
        93,
        95,
        174,
        135,
        154,
        58,
        82,
        76,
        57,
        78,
        74,
        89,
        84,
        86,
        71,
        75,
        76,
        132,
        54,
        70
      ]
    },
    {
      "margin": false,
      "index": 7,
      "file": null,
      "u": 0.3333333,
      "v": 0.109375,
      "uw": 0.3333333,
      "vh": 0.260416657,
      "width": 533,
      "height": 533,
      "descriptor": [
        165,
        76,
        64,
        60,
        63,
        60,
        214,
        98,
        109,
        169,
        91,
        74,
        81,
        103,
        77,
        102,
        105,
        80,
        52,
        62,
        62,
        193,
        151,
        163,
        115,
        146,
        82,
        84,
        84,
        84,
        66,
        68,
        70,
        170,
        152,
        159,
        124,
        93,
        91,
        66,
        78,
        76,
        96,
        73,
        74,
        167,
        111,
        137
      ]
    },
    {
      "margin": false,
      "index": 8,
      "file": null,
      "u": 0.6666666,
      "v": 0.109375,
      "uw": 0.3333333,
      "vh": 0.260416657,
      "width": 533,
      "height": 533,
      "descriptor": [
        93,
        63,
        61,
        110,
        55,
        56,
        73,
        78,
        71,
        87,
        76,
        74,
        119,
        96,
        99,
        105,
        100,
        72,
        114,
        98,
        99,
        80,
        80,
        90,
        85,
        93,
        92,
        120,
        117,
        85,
        94,
        103,
        97,
        97,
        90,
        77,
        94,
        101,
        91,
        90,
        99,
        89,
        120,
        116,
        108,
        127,
        114,
        103
      ]
    },
    {
      "margin": false,
      "index": 9,
      "file": null,
      "u": 0.0,
      "v": 0.369791657,
      "uw": 0.3333333,
      "vh": 0.260416657,
      "width": 533,
      "height": 533,
      "descriptor": [
        60,
        76,
        68,
        90,
        84,
        80,
        134,
        87,
        83,
        211,
        153,
        97,
        72,
        81,
        82,
        68,
        69,
        74,
        181,
        87,
        100,
        82,
        83,
        86,
        94,
        94,
        94,
        105,
        94,
        97,
        145,
        88,
        74,
        166,
        108,
        87,
        120,
        115,
        104,
        102,
        102,
        103,
        207,
        128,
        104,
        213,
        153,
        123
      ]
    },
    {
      "margin": false,
      "index": 10,
      "file": null,
      "u": 0.3333333,
      "v": 0.369791657,
      "uw": 0.3333333,
      "vh": 0.260416657,
      "width": 533,
      "height": 533,
      "descriptor": [
        211,
        188,
        156,
        129,
        101,
        77,
        150,
        99,
        64,
        90,
        88,
        90,
        41,
        75,
        77,
        195,
        144,
        31,
        103,
        102,
        95,
        92,
        67,
        72,
        146,
        88,
        122,
        168,
        77,
        66,
        203,
        178,
        90,
        103,
        94,
        93,
        190,
        149,
        136,
        189,
        144,
        145,
        77,
        82,
        82,
        138,
        124,
        123
      ]
    },
    {
      "margin": false,
      "index": 11,
      "file": null,
      "u": 0.6666666,
      "v": 0.369791657,
      "uw": 0.3333333,
      "vh": 0.260416657,
      "width": 533,
      "height": 533,
      "descriptor": [
        115,
        100,
        82,
        116,
        62,
        64,
        130,
        123,
        99,
        65,
        79,
        83,
        104,
        100,
        96,
        143,
        143,
        130,
        103,
        109,
        79,
        86,
        74,
        80,
        97,
        105,
        90,
        77,
        90,
        80,
        61,
        84,
        83,
        73,
        67,
        70,
        105,
        103,
        83,
        82,
        81,
        74,
        52,
        60,
        59,
        71,
        73,
        70
      ]
    },
    {
      "margin": false,
      "index": 12,
      "file": null,
      "u": 0.0,
      "v": 0.6302083,
      "uw": 0.3333333,
      "vh": 0.260416657,
      "width": 533,
      "height": 533,
      "descriptor": [
        118,
        116,
        67,
        101,
        96,
        94,
        53,
        60,
        60,
        72,
        80,
        78,
        134,
        123,
        79,
        107,
        91,
        79,
        51,
        60,
        58,
        131,
        149,
        105,
        75,
        76,
        62,
        100,
        91,
        75,
        44,
        57,
        56,
        69,
        66,
        67,
        45,
        58,
        55,
        126,
        119,
        114,
        116,
        111,
        107,
        148,
        153,
        131
      ]
    },
    {
      "margin": false,
      "index": 13,
      "file": null,
      "u": 0.3333333,
      "v": 0.6302083,
      "uw": 0.3333333,
      "vh": 0.260416657,
      "width": 533,
      "height": 533,
      "descriptor": [
        180,
        151,
        139,
        124,
        101,
        104,
        161,
        134,
        74,
        157,
        151,
        135,
        77,
        75,
        80,
        191,
        171,
        153,
        71,
        80,
        75,
        160,
        139,
        109,
        204,
        202,
        187,
        143,
        130,
        122,
        69,
        89,
        88,
        142,
        136,
        130,
        126,
        128,
        108,
        154,
        158,
        106,
        52,
        73,
        75,
        91,
        94,
        95
      ]
    },
    {
      "margin": false,
      "index": 14,
      "file": null,
      "u": 0.6666666,
      "v": 0.6302083,
      "uw": 0.3333333,
      "vh": 0.260416657,
      "width": 533,
      "height": 533,
      "descriptor": [
        71,
        88,
        85,
        85,
        96,
        80,
        58,
        63,
        67,
        53,
        58,
        58,
        104,
        87,
        87,
        91,
        87,
        89,
        56,
        57,
        60,
        43,
        58,
        59,
        121,
        149,
        131,
        64,
        65,
        69,
        69,
        72,
        73,
        50,
        58,
        63,
        87,
        105,
        105,
        137,
        134,
        129,
        96,
        103,
        101,
        51,
        63,
        66
      ]
    }
  ],
  "margins": [
    {
      "margin": true,
      "index": 0,
      "file": null,
      "u": 0.0,
      "v": 0.0,
      "uw": 0.3333333,
      "vh": 0.109375,
      "width": 533,
      "height": 224,
      "descriptor": null
    },
    {
      "margin": true,
      "index": 1,
      "file": null,
      "u": 0.0,
      "v": 0.890625,
      "uw": 0.3333333,
      "vh": 0.109375,
      "width": 533,
      "height": 224,
      "descriptor": null
    },
    {
      "margin": true,
      "index": 2,
      "file": null,
      "u": 0.3333333,
      "v": 0.0,
      "uw": 0.3333333,
      "vh": 0.109375,
      "width": 533,
      "height": 224,
      "descriptor": null
    },
    {
      "margin": true,
      "index": 3,
      "file": null,
      "u": 0.3333333,
      "v": 0.890625,
      "uw": 0.3333333,
      "vh": 0.109375,
      "width": 533,
      "height": 224,
      "descriptor": null
    },
    {
      "margin": true,
      "index": 4,
      "file": null,
      "u": 0.6666666,
      "v": 0.0,
      "uw": 0.3333333,
      "vh": 0.109375,
      "width": 533,
      "height": 224,
      "descriptor": null
    },
    {
      "margin": true,
      "index": 5,
      "file": null,
      "u": 0.6666666,
      "v": 0.890625,
      "uw": 0.3333333,
      "vh": 0.109375,
      "width": 533,
      "height": 224,
      "descriptor": null
    }
  ]
}